calisum/__init__.py
calisum/__main__.py
calisum/cli.py
calisum/scraper.py
calisum/util.py
calisum/summarizer/__init__.py
calisum/summarizer/models.py
calisum/summarizer/summarizer.py
calisum-1.1.4.dist-info/METADATA
calisum-1.1.4.dist-info/WHEEL
calisum-1.1.4.dist-info/entry_points.txt
calisum-1.1.4.dist-info/licenses/LICENSE.md
calisum-1.1.4.dist-info/RECORD
